qrlocator/__init__.py
qrlocator/qrlocator.py
qrlocator-0.0.3.dist-info/METADATA
qrlocator-0.0.3.dist-info/WHEEL
qrlocator-0.0.3.dist-info/licenses/LICENSE
qrlocator-0.0.3.dist-info/RECORD
